keyprotect/__init__.py
keyprotect-2.3.1.dist-info/LICENSE
keyprotect-2.3.1.dist-info/METADATA
keyprotect-2.3.1.dist-info/WHEEL
keyprotect-2.3.1.dist-info/top_level.txt
keyprotect-2.3.1.dist-info/RECORD
