Metadata-Version: 2.1
Name: keyprotect
Version: 2.3.1
Summary: A Pythonic client for IBM Key Protect
Home-page: https://github.com/IBM/keyprotect-python-client
Author: Mathew Odden
Author-email: mathewrodden@gmail.com
License: Apache 2.0
Classifier: Operating System :: OS Independent
Classifier: Intended Audience :: Developers
Classifier: Natural Language :: English
Classifier: License :: OSI Approved :: Apache Software License
Classifier: Programming Language :: Python
Classifier: Programming Language :: Python :: 3
Classifier: Programming Language :: Python :: 3.5
Classifier: Programming Language :: Python :: 3.6
Classifier: Programming Language :: Python :: 3.7
Classifier: Programming Language :: Python :: 3.8
Classifier: Programming Language :: Python :: Implementation :: CPython
Classifier: Programming Language :: Python :: Implementation :: PyPy
Requires-Python: >=3.5
License-File: LICENSE
Requires-Dist: redstone (<0.7,>=0.6.0)
